escience/__init__.py
escience/__main__.py
escience/__version__.py
escience/core.py
escience/escience.py
utiles/__init__.py
utiles/logger.py
utiles/process_bar.py
escience-0.1.3.dist-info/LICENSE
escience-0.1.3.dist-info/METADATA
escience-0.1.3.dist-info/WHEEL
escience-0.1.3.dist-info/entry_points.txt
escience-0.1.3.dist-info/top_level.txt
escience-0.1.3.dist-info/RECORD
