Metadata-Version: 2.1
Name: escience
Version: 0.1.3
Summary: escience ClL
Home-page: https://github.com/steinvenic/escience
Author: steinvenior
Author-email: steinvenior@gmail.com
License: MIT
Platform: UNKNOWN
Classifier: License :: OSI Approved :: MIT License
Classifier: Programming Language :: Python
Classifier: Programming Language :: Python :: 3
Classifier: Programming Language :: Python :: 3.6
Classifier: Programming Language :: Python :: Implementation :: CPython
Classifier: Programming Language :: Python :: Implementation :: PyPy
Requires-Python: >=3.3.2
Requires-Dist: requests
Requires-Dist: certifi
Requires-Dist: chardet
Requires-Dist: click
Requires-Dist: idna
Requires-Dist: PTable
Requires-Dist: tqdm
Requires-Dist: urllib3
Requires-Dist: prettytable
